{
  "user_info": {
    "username": "mpfthprblmtq",
    "emails": [
      "ripley307/gmail/com"
    ]
  },
  "urls": [],
  "twitter": [
    {
      "handle": "iamdabinlee",
      "name": "Dabin",
      "keywords": [
        "vinyl",
        "vinyls"
      ]
    },
    {
      "handle": "heyjaron",
      "name": "Jaron",
      "keywords": [
        "vinyl",
        "vinyls"
      ]
    },
    {
      "handle": "Yoe_mase",
      "name": "Yoe Mase",
      "keywords": [
        "vinyl",
        "vinyls"
      ]
    }
  ],
  "reddit": {
    "subreddits": [
      "VinylReleases",
      "VinylCollectors"
    ],
    "keywords": [
      "Deadmau5",
      "Devin Townsend",
      "Porter Robinson",
      "Madeon",
      "Dabin",
      "Skrillex",
      "Said the Sky",
      "Flume",
      "Illenium",
      "Yoe Mase",
      "Mako",
      "Biffy Clyro",
      "Ekali",
      "Eden",
      "Grabbitz",
      "Mitis",
      "Missio",
      "Raleigh Ritchie",
      "You're A Man Now, Boy",
      "You're A Man Now Boy",
      "Tristam",
      "Emmit Fenn",
      "Crywolf",
      "Dead Battery",
      "Odesza",
      "EDM",
      "Mr. Bill",
      "Phantasmagoria"
    ]
  }
}